funcgenom/__init__.py
funcgenom/funcgenom.py
funcgenom-0.1.12.dist-info/LICENSE
funcgenom-0.1.12.dist-info/METADATA
funcgenom-0.1.12.dist-info/WHEEL
funcgenom-0.1.12.dist-info/top_level.txt
funcgenom-0.1.12.dist-info/RECORD
