Metadata-Version: 2.1
Name: funcgenom
Version: 0.1.12
Summary: Classes and functions for functional genomics analysis
Home-page: https://gitlab.com/aaylward/funcgenom
Author: Anthony Aylward
Author-email: aaylward@salk.edu
License: UNKNOWN
Platform: UNKNOWN
Classifier: Programming Language :: Python :: 3
Classifier: License :: OSI Approved :: MIT License
Classifier: Operating System :: OS Independent
License-File: LICENSE
Requires-Dist: coloc
Requires-Dist: py1kgp
Requires-Dist: pyhg19
Requires-Dist: sumstats
